Metadata-Version: 1.0
Name: rpc-queue-manager
Version: 0.2
Summary: A simple library for interacting with RabbitMQ RPC in Django
Home-page: UNKNOWN
Author: Surya Dev Singh
Author-email: surya.dev@careers360.com
License: UNKNOWN
Platform: UNKNOWN
